roku_tui.py
roku_tui-0.1.2.dist-info/LICENSE
roku_tui-0.1.2.dist-info/METADATA
roku_tui-0.1.2.dist-info/WHEEL
roku_tui-0.1.2.dist-info/entry_points.txt
roku_tui-0.1.2.dist-info/top_level.txt
roku_tui-0.1.2.dist-info/RECORD
