Metadata-Version: 2.1
Name: roku-tui
Version: 0.1.2
Summary: A TUI remote for Roku
Home-page: https://github.com/winsbe01/roku-tui
Author: Ben Winston
Author-email: ben@benwinston.us
Project-URL: Source, https://github.com/winsbe01/roku-tui
Keywords: roku,remote,tui,cli
Classifier: Development Status :: 5 - Production/Stable
Classifier: Environment :: Console :: Curses
Classifier: Intended Audience :: End Users/Desktop
Classifier: License :: OSI Approved :: Apache Software License
Classifier: Programming Language :: Python :: 3
Classifier: Programming Language :: Python :: 3.7
Classifier: Programming Language :: Python :: 3.8
Classifier: Programming Language :: Python :: 3.9
Classifier: Programming Language :: Python :: 3.10
Classifier: Programming Language :: Python :: 3.11
Classifier: Programming Language :: Python :: 3 :: Only
Classifier: Topic :: Games/Entertainment
Classifier: Topic :: Utilities
Requires-Python: >=3.7, <4
License-File: LICENSE
